Workbook

Sheet Istruzioni
A1: Cash Flow previsionale 2027 – Immobiliare Uno & Immobiliare Due
A3: OBIETTIVO
A4: Previsione dei flussi di cassa mensili delle due società (e consolidata) e proiezione a 5 anni, con dati per singolo immobile: canoni, sfitti, morosità, IMU, imposta di registro, mutui, manutenzioni ordinarie/straordinarie, imprevisti, compravendite.
A6: COME SI USA
A7: 1. Parametri: scegli la società nel filtro (Tutte / IU / ID), anno, saldi iniziali, % imprevisti e morosità.
A8: 2. Immobili: anagrafica del patrimonio con canone, rendita catastale, valore di mercato, costi ricorrenti. Il foglio calcola IMU, registro, rendimento lordo/netto e incidenza costi per immobile.
A9: 3. Occupazione: 1 = locato / 0 = sfitto per mese. Alimenta canoni e IMU (beni merce: IMU solo sui mesi locati).
A10: 4. Mutui: debito residuo, TAN e rate residue. Calcola rata, interessi, quota capitale e simulazione surroga.
A11: 5. Straordinari: movimenti spot (ritinteggiature, guasti, rateizzazioni arretrati, acquisti/vendite immobili).
A12: 6. Cash Flow: risultato mensile; Proiezione 5 anni: medio-lungo termine; KPI Patrimonio: sintesi per società.
A14: COLLEGAMENTO CON ODOO
A15: In Odoo il file si apre da Documenti come foglio di calcolo. Le righe consuntive possono essere sostituite con formule ODOO.BALANCE / ODOO.PIVOT (es. incassi reali dal registro Banca, fatture canoni da Abbonamenti, rate mutui dal modulo Prestiti) per confrontare previsto vs consuntivo.
... A20: Celle gialle = dati da inserire/modificare. Celle bianche = formule.

Sheet Cash Flow
A1: Cash Flow previsionale 2027
A2: ="Società: "&Parametri!B3&" (cambia il filtro nel foglio Parametri)" -> Società: Tutte (cambia il filtro nel foglio Parametri)
A4: Voce | B4: =DATE(Parametri!$B$4,1,1) -> 46388 | C4: =DATE(Parametri!$B$4,2,1) -> 46419 | D4: =DATE(Parametri!$B$4,3,1) -> 46447 | E4: =DATE(Parametri!$B$4,4,1) -> 46478 | F4: =DATE(Parametri!$B$4,5,1) -> 46508 | G4: =DATE(Parametri!$B$4,6,1) -> 46539 | H4: =DATE(Parametri!$B$4,7,1) -> 46569 | I4: =DATE(Parametri!$B$4,8,1) -> 46600 | J4: =DATE(Parametri!$B$4,9,1) -> 46631 | K4: =DATE(Parametri!$B$4,10,1) -> 46661 | L4: =DATE(Parametri!$B$4,11,1) -> 46692 | M4: =DATE(Parametri!$B$4,12,1) -> 46722 | N4: Totale anno
A5: ENTRATE
A6: Canoni di locazione (esenti IVA art.10) | B6: =SUMPRODUCT(Immobili!$AC$5:$AC$16,Immobili!$I$5:$I$16,Occupazione!C$5:C$16) -> 23370 | C6: =SUMPRODUCT(Immobili!$AC$5:$AC$16,Immobili!$I$5:$I$16,Occupazione!D$5:D$16) -> 23370 | D6: =SUMPRODUCT(Immobili!$AC$5:$AC$16,Immobili!$I$5:$I$16,Occupazione!E$5:E$16) -> 23370 | E6: =SUMPRODUCT(Immobili!$AC$5:$AC$16,Immobili!$I$5:$I$16,Occupazione!F$5:F$16) -> 22270 | F6: =SUMPRODUCT(Immobili!$AC$5:$AC$16,Immobili!$I$5:$I$16,Occupazione!G$5:G$16) -> 22270 | G6: =SUMPRODUCT(Immobili!$AC$5:$AC$16,Immobili!$I$5:$I$16,Occupazione!H$5:H$16) -> 22270 | H6: =SUMPRODUCT(Immobili!$AC$5:$AC$16,Immobili!$I$5:$I$16,Occupazione!I$5:I$16) -> 22270 | I6: =SUMPRODUCT(Immobili!$AC$5:$AC$16,Immobili!$I$5:$I$16,Occupazione!J$5:J$16) -> 22270 | ... M6: =SUMPRODUCT(Immobili!$AC$5:$AC$16,Immobili!$I$5:$I$16,Occupazione!N$5:N$16) -> 23370 | N6: =SUM(B6:M6) -> 274940
A7: Morosità attesa | B7: =-B6*Parametri!$B$12 -> -467.4 | C7: =-C6*Parametri!$B$12 -> -467.4 | D7: =-D6*Parametri!$B$12 -> -467.4 | E7: =-E6*Parametri!$B$12 -> -445.4 | F7: =-F6*Parametri!$B$12 -> -445.4 | G7: =-G6*Parametri!$B$12 -> -445.4 | H7: =-H6*Parametri!$B$12 -> -445.4 | I7: =-I6*Parametri!$B$12 -> -445.4 | ... M7: =-M6*Parametri!$B$12 -> -467.4 | N7: =SUM(B7:M7) -> -5498.8
A8: Rateizzazioni arretrati incassate | B8: =SUMIFS(Straordinari!$F$5:$F$64,Straordinari!$G$5:$G$64,1,Straordinari!$D$5:$D$64,"Rateizzazione arretrati",Straordinari!$A$5:$A$64,">="&B$4,Straordinari!$A$5:$A$64,"<"&EDATE(B$4,1)) -> 0 | C8: =SUMIFS(Straordinari!$F$5:$F$64,Straordinari!$G$5:$G$64,1,Straordinari!$D$5:$D$64,"Rateizzazione arretrati",Straordinari!$A$5:$A$64,">="&C$4,Straordinari!$A$5:$A$64,"<"&EDATE(C$4,1)) -> 2600 | D8: =SUMIFS(Straordinari!$F$5:$F$64,Straordinari!$G$5:$G$64,1,Straordinari!$D$5:$D$64,"Rateizzazione arretrati",Straordinari!$A$5:$A$64,">="&D$4,Straordinari!$A$5:$A$64,"<"&EDATE(D$4,1)) -> 2600 | E8: =SUMIFS(Straordinari!$F$5:$F$64,Straordinari!$G$5:$G$64,1,Straordinari!$D$5:$D$64,"Rateizzazione arretrati",Straordinari!$A$5:$A$64,">="&E$4,Straordinari!$A$5:$A$64,"<"&EDATE(E$4,1)) -> 2600 | F8: =SUMIFS(Straordinari!$F$5:$F$64,Straordinari!$G$5:$G$64,1,Straordinari!$D$5:$D$64,"Rateizzazione arretrati",Straordinari!$A$5:$A$64,">="&F$4,Straordinari!$A$5:$A$64,"<"&EDATE(F$4,1)) -> 2600 | G8: =SUMIFS(Straordinari!$F$5:$F$64,Straordinari!$G$5:$G$64,1,Straordinari!$D$5:$D$64,"Rateizzazione arretrati",Straordinari!$A$5:$A$64,">="&G$4,Straordinari!$A$5:$A$64,"<"&EDATE(G$4,1)) -> 2600 | H8: =SUMIFS(Straordinari!$F$5:$F$64,Straordinari!$G$5:$G$64,1,Straordinari!$D$5:$D$64,"Rateizzazione arretrati",Straordinari!$A$5:$A$64,">="&H$4,Straordinari!$A$5:$A$64,"<"&EDATE(H$4,1)) -> 2600 | I8: =SUMIFS(Straordinari!$F$5:$F$64,Straordinari!$G$5:$G$64,1,Straordinari!$D$5:$D$64,"Rateizzazione arretrati",Straordinari!$A$5:$A$64,">="&I$4,Straordinari!$A$5:$A$64,"<"&EDATE(I$4,1)) -> 0 | ... M8: =SUMIFS(Straordinari!$F$5:$F$64,Straordinari!$G$5:$G$64,1,Straordinari!$D$5:$D$64,"Rateizzazione arretrati",Straordinari!$A$5:$A$64,">="&M$4,Straordinari!$A$5:$A$64,"<"&EDATE(M$4,1)) -> 0 | N8: =SUM(B8:M8) -> 15600
A9: Vendite immobili | B9: =SUMIFS(Straordinari!$F$5:$F$64,Straordinari!$G$5:$G$64,1,Straordinari!$D$5:$D$64,"Compravendita",Straordinari!$A$5:$A$64,">="&B$4,Straordinari!$A$5:$A$64,"<"&EDATE(B$4,1),Straordinari!$F$5:$F$64,">0") -> 0 | C9: =SUMIFS(Straordinari!$F$5:$F$64,Straordinari!$G$5:$G$64,1,Straordinari!$D$5:$D$64,"Compravendita",Straordinari!$A$5:$A$64,">="&C$4,Straordinari!$A$5:$A$64,"<"&EDATE(C$4,1),Straordinari!$F$5:$F$64,">0") -> 0 | D9: =SUMIFS(Straordinari!$F$5:$F$64,Straordinari!$G$5:$G$64,1,Straordinari!$D$5:$D$64,"Compravendita",Straordinari!$A$5:$A$64,">="&D$4,Straordinari!$A$5:$A$64,"<"&EDATE(D$4,1),Straordinari!$F$5:$F$64,">0") -> 0 | E9: =SUMIFS(Straordinari!$F$5:$F$64,Straordinari!$G$5:$G$64,1,Straordinari!$D$5:$D$64,"Compravendita",Straordinari!$A$5:$A$64,">="&E$4,Straordinari!$A$5:$A$64,"<"&EDATE(E$4,1),Straordinari!$F$5:$F$64,">0") -> 0 | F9: =SUMIFS(Straordinari!$F$5:$F$64,Straordinari!$G$5:$G$64,1,Straordinari!$D$5:$D$64,"Compravendita",Straordinari!$A$5:$A$64,">="&F$4,Straordinari!$A$5:$A$64,"<"&EDATE(F$4,1),Straordinari!$F$5:$F$64,">0") -> 0 | G9: =SUMIFS(Straordinari!$F$5:$F$64,Straordinari!$G$5:$G$64,1,Straordinari!$D$5:$D$64,"Compravendita",Straordinari!$A$5:$A$64,">="&G$4,Straordinari!$A$5:$A$64,"<"&EDATE(G$4,1),Straordinari!$F$5:$F$64,">0") -> 0 | H9: =SUMIFS(Straordinari!$F$5:$F$64,Straordinari!$G$5:$G$64,1,Straordinari!$D$5:$D$64,"Compravendita",Straordinari!$A$5:$A$64,">="&H$4,Straordinari!$A$5:$A$64,"<"&EDATE(H$4,1),Straordinari!$F$5:$F$64,">0") -> 0 | I9: =SUMIFS(Straordinari!$F$5:$F$64,Straordinari!$G$5:$G$64,1,Straordinari!$D$5:$D$64,"Compravendita",Straordinari!$A$5:$A$64,">="&I$4,Straordinari!$A$5:$A$64,"<"&EDATE(I$4,1),Straordinari!$F$5:$F$64,">0") -> 0 | ... M9: =SUMIFS(Straordinari!$F$5:$F$64,Straordinari!$G$5:$G$64,1,Straordinari!$D$5:$D$64,"Compravendita",Straordinari!$A$5:$A$64,">="&M$4,Straordinari!$A$5:$A$64,"<"&EDATE(M$4,1),Straordinari!$F$5:$F$64,">0") -> 0 | N9: =SUM(B9:M9) -> 21000
A10: Totale entrate | B10: =SUM(B6:B9) -> 22902.6 | C10: =SUM(C6:C9) -> 25502.6 | D10: =SUM(D6:D9) -> 25502.6 | E10: =SUM(E6:E9) -> 24424.6 | F10: =SUM(F6:F9) -> 24424.6 | G10: =SUM(G6:G9) -> 24424.6 | H10: =SUM(H6:H9) -> 24424.6 | I10: =SUM(I6:I9) -> 21824.6 | ... M10: =SUM(M6:M9) -> 22902.6 | N10: =SUM(B10:M10) -> 306041.2
A12: USCITE
A13: Rate mutui e finanziamenti | B13: =-SUMIFS(Mutui!$H$5:$H$8,Mutui!$O$5:$O$8,1,Mutui!$G$5:$G$8,">="&1) -> -9387.5794 | C13: =-SUMIFS(Mutui!$H$5:$H$8,Mutui!$O$5:$O$8,1,Mutui!$G$5:$G$8,">="&2) -> -9387.5794 | D13: =-SUMIFS(Mutui!$H$5:$H$8,Mutui!$O$5:$O$8,1,Mutui!$G$5:$G$8,">="&3) -> -9387.5794 | E13: =-SUMIFS(Mutui!$H$5:$H$8,Mutui!$O$5:$O$8,1,Mutui!$G$5:$G$8,">="&4) -> -9387.5794 | F13: =-SUMIFS(Mutui!$H$5:$H$8,Mutui!$O$5:$O$8,1,Mutui!$G$5:$G$8,">="&5) -> -9387.5794 | G13: =-SUMIFS(Mutui!$H$5:$H$8,Mutui!$O$5:$O$8,1,Mutui!$G$5:$G$8,">="&6) -> -9387.5794 | H13: =-SUMIFS(Mutui!$H$5:$H$8,Mutui!$O$5:$O$8,1,Mutui!$G$5:$G$8,">="&7) -> -9387.5794 | I13: =-SUMIFS(Mutui!$H$5:$H$8,Mutui!$O$5:$O$8,1,Mutui!$G$5:$G$8,">="&8) -> -9387.5794 | J13: =-SUMIFS(Mutui!$H$5:$H$8,Mutui!$O$5:$O$8,1,Mutui!$G$5:$G$8,">="&9) -> -9387.5794 | K13: =-SUMIFS(Mutui!$H$5:$H$8,Mutui!$O$5:$O$8,1,Mutui!$G$5:$G$8,">="&10) -> -9387.5794 | L13: =-SUMIFS(Mutui!$H$5:$H$8,Mutui!$O$5:$O$8,1,Mutui!$G$5:$G$8,">="&11) -> -9387.5794 | M13: =-SUMIFS(Mutui!$H$5:$H$8,Mutui!$O$5:$O$8,1,Mutui!$G$5:$G$8,">="&12) -> -9387.5794 | N13: =SUM(B13:M13) -> -112650.95
A14: IMU (acconto 16/06 – saldo 16/12) | B14: =IF(MONTH(B$4)=6,-SUMIFS(Immobili!$T$5:$T$16,Immobili!$AC$5:$AC$16,1),IF(MONTH(B$4)=12,-(SUMIFS(Immobili!$U$5:$U$16,Immobili!$AC$5:$AC$16,1)-SUMIFS(Immobili!$T$5:$T$16,Immobili!$AC$5:$AC$16,1)),0)) -> 0 | C14: =IF(MONTH(C$4)=6,-SUMIFS(Immobili!$T$5:$T$16,Immobili!$AC$5:$AC$16,1),IF(MONTH(C$4)=12,-(SUMIFS(Immobili!$U$5:$U$16,Immobili!$AC$5:$AC$16,1)-SUMIFS(Immobili!$T$5:$T$16,Immobili!$AC$5:$AC$16,1)),0)) -> 0 | D14: =IF(MONTH(D$4)=6,-SUMIFS(Immobili!$T$5:$T$16,Immobili!$AC$5:$AC$16,1),IF(MONTH(D$4)=12,-(SUMIFS(Immobili!$U$5:$U$16,Immobili!$AC$5:$AC$16,1)-SUMIFS(Immobili!$T$5:$T$16,Immobili!$AC$5:$AC$16,1)),0)) -> 0 | E14: =IF(MONTH(E$4)=6,-SUMIFS(Immobili!$T$5:$T$16,Immobili!$AC$5:$AC$16,1),IF(MONTH(E$4)=12,-(SUMIFS(Immobili!$U$5:$U$16,Immobili!$AC$5:$AC$16,1)-SUMIFS(Immobili!$T$5:$T$16,Immobili!$AC$5:$AC$16,1)),0)) -> 0 | F14: =IF(MONTH(F$4)=6,-SUMIFS(Immobili!$T$5:$T$16,Immobili!$AC$5:$AC$16,1),IF(MONTH(F$4)=12,-(SUMIFS(Immobili!$U$5:$U$16,Immobili!$AC$5:$AC$16,1)-SUMIFS(Immobili!$T$5:$T$16,Immobili!$AC$5:$AC$16,1)),0)) -> 0 | G14: =IF(MONTH(G$4)=6,-SUMIFS(Immobili!$T$5:$T$16,Immobili!$AC$5:$AC$16,1),IF(MONTH(G$4)=12,-(SUMIFS(Immobili!$U$5:$U$16,Immobili!$AC$5:$AC$16,1)-SUMIFS(Immobili!$T$5:$T$16,Immobili!$AC$5:$AC$16,1)),0)) -> -12170.87 | H14: =IF(MONTH(H$4)=6,-SUMIFS(Immobili!$T$5:$T$16,Immobili!$AC$5:$AC$16,1),IF(MONTH(H$4)=12,-(SUMIFS(Immobili!$U$5:$U$16,Immobili!$AC$5:$AC$16,1)-SUMIFS(Immobili!$T$5:$T$16,Immobili!$AC$5:$AC$16,1)),0)) -> 0 | I14: =IF(MONTH(I$4)=6,-SUMIFS(Immobili!$T$5:$T$16,Immobili!$AC$5:$AC$16,1),IF(MONTH(I$4)=12,-(SUMIFS(Immobili!$U$5:$U$16,Immobili!$AC$5:$AC$16,1)-SUMIFS(Immobili!$T$5:$T$16,Immobili!$AC$5:$AC$16,1)),0)) -> 0 | ... M14: =IF(MONTH(M$4)=6,-SUMIFS(Immobili!$T$5:$T$16,Immobili!$AC$5:$AC$16,1),IF(MONTH(M$4)=12,-(SUMIFS(Immobili!$U$5:$U$16,Immobili!$AC$5:$AC$16,1)-SUMIFS(Immobili!$T$5:$T$16,Immobili!$AC$5:$AC$16,1)),0)) -> -12350.75 | N14: =SUM(B14:M14) -> -24521.62
A15: Imposta di registro annuale | B15: =-SUMIFS(Immobili!$V$5:$V$16,Immobili!$AC$5:$AC$16,1,Immobili!$K$5:$K$16,MONTH(B$4)) -> -660 | C15: =-SUMIFS(Immobili!$V$5:$V$16,Immobili!$AC$5:$AC$16,1,Immobili!$K$5:$K$16,MONTH(C$4)) -> -312 | D15: =-SUMIFS(Immobili!$V$5:$V$16,Immobili!$AC$5:$AC$16,1,Immobili!$K$5:$K$16,MONTH(D$4)) -> -276 | E15: =-SUMIFS(Immobili!$V$5:$V$16,Immobili!$AC$5:$AC$16,1,Immobili!$K$5:$K$16,MONTH(E$4)) -> -204 | F15: =-SUMIFS(Immobili!$V$5:$V$16,Immobili!$AC$5:$AC$16,1,Immobili!$K$5:$K$16,MONTH(F$4)) -> -348 | G15: =-SUMIFS(Immobili!$V$5:$V$16,Immobili!$AC$5:$AC$16,1,Immobili!$K$5:$K$16,MONTH(G$4)) -> -240 | H15: =-SUMIFS(Immobili!$V$5:$V$16,Immobili!$AC$5:$AC$16,1,Immobili!$K$5:$K$16,MONTH(H$4)) -> -264 | I15: =-SUMIFS(Immobili!$V$5:$V$16,Immobili!$AC$5:$AC$16,1,Immobili!$K$5:$K$16,MONTH(I$4)) -> 0 | ... M15: =-SUMIFS(Immobili!$V$5:$V$16,Immobili!$AC$5:$AC$16,1,Immobili!$K$5:$K$16,MONTH(M$4)) -> 0 | N15: =SUM(B15:M15) -> -3352.8
A16: Spese condominiali (quota proprietà) | B16: =-SUMIFS(Immobili!$M$5:$M$16,Immobili!$AC$5:$AC$16,1) -> -1230 | C16: =-SUMIFS(Immobili!$M$5:$M$16,Immobili!$AC$5:$AC$16,1) -> -1230 | D16: =-SUMIFS(Immobili!$M$5:$M$16,Immobili!$AC$5:$AC$16,1) -> -1230 | E16: =-SUMIFS(Immobili!$M$5:$M$16,Immobili!$AC$5:$AC$16,1) -> -1230 | F16: =-SUMIFS(Immobili!$M$5:$M$16,Immobili!$AC$5:$AC$16,1) -> -1230 | G16: =-SUMIFS(Immobili!$M$5:$M$16,Immobili!$AC$5:$AC$16,1) -> -1230 | H16: =-SUMIFS(Immobili!$M$5:$M$16,Immobili!$AC$5:$AC$16,1) -> -1230 | I16: =-SUMIFS(Immobili!$M$5:$M$16,Immobili!$AC$5:$AC$16,1) -> -1230 | ... M16: =-SUMIFS(Immobili!$M$5:$M$16,Immobili!$AC$5:$AC$16,1) -> -1230 | N16: =SUM(B16:M16) -> -14760
A17: Manutenzione ordinaria programmata | B17: =-SUMIFS(Immobili!$N$5:$N$16,Immobili!$AC$5:$AC$16,1)/12 -> -641.66667 | C17: =-SUMIFS(Immobili!$N$5:$N$16,Immobili!$AC$5:$AC$16,1)/12 -> -641.66667 | D17: =-SUMIFS(Immobili!$N$5:$N$16,Immobili!$AC$5:$AC$16,1)/12 -> -641.66667 | E17: =-SUMIFS(Immobili!$N$5:$N$16,Immobili!$AC$5:$AC$16,1)/12 -> -641.66667 | F17: =-SUMIFS(Immobili!$N$5:$N$16,Immobili!$AC$5:$AC$16,1)/12 -> -641.66667 | G17: =-SUMIFS(Immobili!$N$5:$N$16,Immobili!$AC$5:$AC$16,1)/12 -> -641.66667 | H17: =-SUMIFS(Immobili!$N$5:$N$16,Immobili!$AC$5:$AC$16,1)/12 -> -641.66667 | I17: =-SUMIFS(Immobili!$N$5:$N$16,Immobili!$AC$5:$AC$16,1)/12 -> -641.66667 | ... M17: =-SUMIFS(Immobili!$N$5:$N$16,Immobili!$AC$5:$AC$16,1)/12 -> -641.66667 | N17: =SUM(B17:M17) -> -7700
A18: Manutenzioni straordinarie / ritinteggiature | B18: =SUMIFS(Straordinari!$F$5:$F$64,Straordinari!$G$5:$G$64,1,Straordinari!$D$5:$D$64,"Manutenzione straordinaria",Straordinari!$A$5:$A$64,">="&B$4,Straordinari!$A$5:$A$64,"<"&EDATE(B$4,1)) -> 0 | C18: =SUMIFS(Straordinari!$F$5:$F$64,Straordinari!$G$5:$G$64,1,Straordinari!$D$5:$D$64,"Manutenzione straordinaria",Straordinari!$A$5:$A$64,">="&C$4,Straordinari!$A$5:$A$64,"<"&EDATE(C$4,1)) -> 0 | D18: =SUMIFS(Straordinari!$F$5:$F$64,Straordinari!$G$5:$G$64,1,Straordinari!$D$5:$D$64,"Manutenzione straordinaria",Straordinari!$A$5:$A$64,">="&D$4,Straordinari!$A$5:$A$64,"<"&EDATE(D$4,1)) -> -12500 | E18: =SUMIFS(Straordinari!$F$5:$F$64,Straordinari!$G$5:$G$64,1,Straordinari!$D$5:$D$64,"Manutenzione straordinaria",Straordinari!$A$5:$A$64,">="&E$4,Straordinari!$A$5:$A$64,"<"&EDATE(E$4,1)) -> -2800 | F18: =SUMIFS(Straordinari!$F$5:$F$64,Straordinari!$G$5:$G$64,1,Straordinari!$D$5:$D$64,"Manutenzione straordinaria",Straordinari!$A$5:$A$64,">="&F$4,Straordinari!$A$5:$A$64,"<"&EDATE(F$4,1)) -> -1900 | G18: =SUMIFS(Straordinari!$F$5:$F$64,Straordinari!$G$5:$G$64,1,Straordinari!$D$5:$D$64,"Manutenzione straordinaria",Straordinari!$A$5:$A$64,">="&G$4,Straordinari!$A$5:$A$64,"<"&EDATE(G$4,1)) -> 0 | H18: =SUMIFS(Straordinari!$F$5:$F$64,Straordinari!$G$5:$G$64,1,Straordinari!$D$5:$D$64,"Manutenzione straordinaria",Straordinari!$A$5:$A$64,">="&H$4,Straordinari!$A$5:$A$64,"<"&EDATE(H$4,1)) -> -4200 | I18: =SUMIFS(Straordinari!$F$5:$F$64,Straordinari!$G$5:$G$64,1,Straordinari!$D$5:$D$64,"Manutenzione straordinaria",Straordinari!$A$5:$A$64,">="&I$4,Straordinari!$A$5:$A$64,"<"&EDATE(I$4,1)) -> 0 | ... M18: =SUMIFS(Straordinari!$F$5:$F$64,Straordinari!$G$5:$G$64,1,Straordinari!$D$5:$D$64,"Manutenzione straordinaria",Straordinari!$A$5:$A$64,">="&M$4,Straordinari!$A$5:$A$64,"<"&EDATE(M$4,1)) -> 0 | N18: =SUM(B18:M18) -> -22500
A19: Imprevisti (accantonamento) | B19: =-B6*Parametri!$B$11 -> -701.1 | C19: =-C6*Parametri!$B$11 -> -701.1 | D19: =-D6*Parametri!$B$11 -> -701.1 | E19: =-E6*Parametri!$B$11 -> -668.1 | F19: =-F6*Parametri!$B$11 -> -668.1 | G19: =-G6*Parametri!$B$11 -> -668.1 | H19: =-H6*Parametri!$B$11 -> -668.1 | I19: =-I6*Parametri!$B$11 -> -668.1 | ... M19: =-M6*Parametri!$B$11 -> -701.1 | N19: =SUM(B19:M19) -> -8248.2
A20: Assicurazioni | B20: =IF(MONTH(B$4)=Parametri!$B$13,-SUMIFS(Parametri!$E$7:$E$8,Parametri!$G$7:$G$8,1),0) -> -11000 | C20: =IF(MONTH(C$4)=Parametri!$B$13,-SUMIFS(Parametri!$E$7:$E$8,Parametri!$G$7:$G$8,1),0) -> 0 | D20: =IF(MONTH(D$4)=Parametri!$B$13,-SUMIFS(Parametri!$E$7:$E$8,Parametri!$G$7:$G$8,1),0) -> 0 | E20: =IF(MONTH(E$4)=Parametri!$B$13,-SUMIFS(Parametri!$E$7:$E$8,Parametri!$G$7:$G$8,1),0) -> 0 | F20: =IF(MONTH(F$4)=Parametri!$B$13,-SUMIFS(Parametri!$E$7:$E$8,Parametri!$G$7:$G$8,1),0) -> 0 | G20: =IF(MONTH(G$4)=Parametri!$B$13,-SUMIFS(Parametri!$E$7:$E$8,Parametri!$G$7:$G$8,1),0) -> 0 | H20: =IF(MONTH(H$4)=Parametri!$B$13,-SUMIFS(Parametri!$E$7:$E$8,Parametri!$G$7:$G$8,1),0) -> 0 | I20: =IF(MONTH(I$4)=Parametri!$B$13,-SUMIFS(Parametri!$E$7:$E$8,Parametri!$G$7:$G$8,1),0) -> 0 | ... M20: =IF(MONTH(M$4)=Parametri!$B$13,-SUMIFS(Parametri!$E$7:$E$8,Parametri!$G$7:$G$8,1),0) -> 0 | N20: =SUM(B20:M20) -> -11000
A21: Commercialista e consulenze | B21: =-SUMIFS(Parametri!$F$7:$F$8,Parametri!$G$7:$G$8,1) -> -1200 | C21: =-SUMIFS(Parametri!$F$7:$F$8,Parametri!$G$7:$G$8,1) -> -1200 | D21: =-SUMIFS(Parametri!$F$7:$F$8,Parametri!$G$7:$G$8,1) -> -1200 | E21: =-SUMIFS(Parametri!$F$7:$F$8,Parametri!$G$7:$G$8,1) -> -1200 | F21: =-SUMIFS(Parametri!$F$7:$F$8,Parametri!$G$7:$G$8,1) -> -1200 | G21: =-SUMIFS(Parametri!$F$7:$F$8,Parametri!$G$7:$G$8,1) -> -1200 | H21: =-SUMIFS(Parametri!$F$7:$F$8,Parametri!$G$7:$G$8,1) -> -1200 | I21: =-SUMIFS(Parametri!$F$7:$F$8,Parametri!$G$7:$G$8,1) -> -1200 | ... M21: =-SUMIFS(Parametri!$F$7:$F$8,Parametri!$G$7:$G$8,1) -> -1200 | N21: =SUM(B21:M21) -> -14400
A22: Imposte dirette (IRES/IRAP) | B22: =-SUMIFS(Parametri!$D$7:$D$8,Parametri!$G$7:$G$8,1)*IF(MONTH(B$4)=6,Parametri!$B$14,IF(MONTH(B$4)=11,Parametri!$B$15,0)) -> 0 | C22: =-SUMIFS(Parametri!$D$7:$D$8,Parametri!$G$7:$G$8,1)*IF(MONTH(C$4)=6,Parametri!$B$14,IF(MONTH(C$4)=11,Parametri!$B$15,0)) -> 0 | D22: =-SUMIFS(Parametri!$D$7:$D$8,Parametri!$G$7:$G$8,1)*IF(MONTH(D$4)=6,Parametri!$B$14,IF(MONTH(D$4)=11,Parametri!$B$15,0)) -> 0 | E22: =-SUMIFS(Parametri!$D$7:$D$8,Parametri!$G$7:$G$8,1)*IF(MONTH(E$4)=6,Parametri!$B$14,IF(MONTH(E$4)=11,Parametri!$B$15,0)) -> 0 | F22: =-SUMIFS(Parametri!$D$7:$D$8,Parametri!$G$7:$G$8,1)*IF(MONTH(F$4)=6,Parametri!$B$14,IF(MONTH(F$4)=11,Parametri!$B$15,0)) -> 0 | G22: =-SUMIFS(Parametri!$D$7:$D$8,Parametri!$G$7:$G$8,1)*IF(MONTH(G$4)=6,Parametri!$B$14,IF(MONTH(G$4)=11,Parametri!$B$15,0)) -> -12000 | H22: =-SUMIFS(Parametri!$D$7:$D$8,Parametri!$G$7:$G$8,1)*IF(MONTH(H$4)=6,Parametri!$B$14,IF(MONTH(H$4)=11,Parametri!$B$15,0)) -> 0 | I22: =-SUMIFS(Parametri!$D$7:$D$8,Parametri!$G$7:$G$8,1)*IF(MONTH(I$4)=6,Parametri!$B$14,IF(MONTH(I$4)=11,Parametri!$B$15,0)) -> 0 | ... M22: =-SUMIFS(Parametri!$D$7:$D$8,Parametri!$G$7:$G$8,1)*IF(MONTH(M$4)=6,Parametri!$B$14,IF(MONTH(M$4)=11,Parametri!$B$15,0)) -> 0 | N22: =SUM(B22:M22) -> -30000
A23: Spese commerciali (annunci, agenzie) | B23: =SUMIFS(Straordinari!$F$5:$F$64,Straordinari!$G$5:$G$64,1,Straordinari!$D$5:$D$64,"Commerciale",Straordinari!$A$5:$A$64,">="&B$4,Straordinari!$A$5:$A$64,"<"&EDATE(B$4,1)) -> 0 | C23: =SUMIFS(Straordinari!$F$5:$F$64,Straordinari!$G$5:$G$64,1,Straordinari!$D$5:$D$64,"Commerciale",Straordinari!$A$5:$A$64,">="&C$4,Straordinari!$A$5:$A$64,"<"&EDATE(C$4,1)) -> 0 | D23: =SUMIFS(Straordinari!$F$5:$F$64,Straordinari!$G$5:$G$64,1,Straordinari!$D$5:$D$64,"Commerciale",Straordinari!$A$5:$A$64,">="&D$4,Straordinari!$A$5:$A$64,"<"&EDATE(D$4,1)) -> 0 | E23: =SUMIFS(Straordinari!$F$5:$F$64,Straordinari!$G$5:$G$64,1,Straordinari!$D$5:$D$64,"Commerciale",Straordinari!$A$5:$A$64,">="&E$4,Straordinari!$A$5:$A$64,"<"&EDATE(E$4,1)) -> 0 | F23: =SUMIFS(Straordinari!$F$5:$F$64,Straordinari!$G$5:$G$64,1,Straordinari!$D$5:$D$64,"Commerciale",Straordinari!$A$5:$A$64,">="&F$4,Straordinari!$A$5:$A$64,"<"&EDATE(F$4,1)) -> 0 | G23: =SUMIFS(Straordinari!$F$5:$F$64,Straordinari!$G$5:$G$64,1,Straordinari!$D$5:$D$64,"Commerciale",Straordinari!$A$5:$A$64,">="&G$4,Straordinari!$A$5:$A$64,"<"&EDATE(G$4,1)) -> -350 | H23: =SUMIFS(Straordinari!$F$5:$F$64,Straordinari!$G$5:$G$64,1,Straordinari!$D$5:$D$64,"Commerciale",Straordinari!$A$5:$A$64,">="&H$4,Straordinari!$A$5:$A$64,"<"&EDATE(H$4,1)) -> 0 | I23: =SUMIFS(Straordinari!$F$5:$F$64,Straordinari!$G$5:$G$64,1,Straordinari!$D$5:$D$64,"Commerciale",Straordinari!$A$5:$A$64,">="&I$4,Straordinari!$A$5:$A$64,"<"&EDATE(I$4,1)) -> 0 | ... M23: =SUMIFS(Straordinari!$F$5:$F$64,Straordinari!$G$5:$G$64,1,Straordinari!$D$5:$D$64,"Commerciale",Straordinari!$A$5:$A$64,">="&M$4,Straordinari!$A$5:$A$64,"<"&EDATE(M$4,1)) -> 0 | N23: =SUM(B23:M23) -> -350
A24: Investimenti / acquisti immobili | B24: =SUMIFS(Straordinari!$F$5:$F$64,Straordinari!$G$5:$G$64,1,Straordinari!$D$5:$D$64,"Compravendita",Straordinari!$A$5:$A$64,">="&B$4,Straordinari!$A$5:$A$64,"<"&EDATE(B$4,1),Straordinari!$F$5:$F$64,"<0") -> 0 | C24: =SUMIFS(Straordinari!$F$5:$F$64,Straordinari!$G$5:$G$64,1,Straordinari!$D$5:$D$64,"Compravendita",Straordinari!$A$5:$A$64,">="&C$4,Straordinari!$A$5:$A$64,"<"&EDATE(C$4,1),Straordinari!$F$5:$F$64,"<0") -> 0 | D24: =SUMIFS(Straordinari!$F$5:$F$64,Straordinari!$G$5:$G$64,1,Straordinari!$D$5:$D$64,"Compravendita",Straordinari!$A$5:$A$64,">="&D$4,Straordinari!$A$5:$A$64,"<"&EDATE(D$4,1),Straordinari!$F$5:$F$64,"<0") -> 0 | E24: =SUMIFS(Straordinari!$F$5:$F$64,Straordinari!$G$5:$G$64,1,Straordinari!$D$5:$D$64,"Compravendita",Straordinari!$A$5:$A$64,">="&E$4,Straordinari!$A$5:$A$64,"<"&EDATE(E$4,1),Straordinari!$F$5:$F$64,"<0") -> 0 | F24: =SUMIFS(Straordinari!$F$5:$F$64,Straordinari!$G$5:$G$64,1,Straordinari!$D$5:$D$64,"Compravendita",Straordinari!$A$5:$A$64,">="&F$4,Straordinari!$A$5:$A$64,"<"&EDATE(F$4,1),Straordinari!$F$5:$F$64,"<0") -> 0 | G24: =SUMIFS(Straordinari!$F$5:$F$64,Straordinari!$G$5:$G$64,1,Straordinari!$D$5:$D$64,"Compravendita",Straordinari!$A$5:$A$64,">="&G$4,Straordinari!$A$5:$A$64,"<"&EDATE(G$4,1),Straordinari!$F$5:$F$64,"<0") -> 0 | H24: =SUMIFS(Straordinari!$F$5:$F$64,Straordinari!$G$5:$G$64,1,Straordinari!$D$5:$D$64,"Compravendita",Straordinari!$A$5:$A$64,">="&H$4,Straordinari!$A$5:$A$64,"<"&EDATE(H$4,1),Straordinari!$F$5:$F$64,"<0") -> 0 | I24: =SUMIFS(Straordinari!$F$5:$F$64,Straordinari!$G$5:$G$64,1,Straordinari!$D$5:$D$64,"Compravendita",Straordinari!$A$5:$A$64,">="&I$4,Straordinari!$A$5:$A$64,"<"&EDATE(I$4,1),Straordinari!$F$5:$F$64,"<0") -> 0 | ... M24: =SUMIFS(Straordinari!$F$5:$F$64,Straordinari!$G$5:$G$64,1,Straordinari!$D$5:$D$64,"Compravendita",Straordinari!$A$5:$A$64,">="&M$4,Straordinari!$A$5:$A$64,"<"&EDATE(M$4,1),Straordinari!$F$5:$F$64,"<0") -> 0 | N24: =SUM(B24:M24) -> -40000
A25: Totale uscite | B25: =SUM(B13:B24) -> -24820.346 | C25: =SUM(C13:C24) -> -13472.346 | D25: =SUM(D13:D24) -> -25936.346 | E25: =SUM(E13:E24) -> -16131.346 | F25: =SUM(F13:F24) -> -15375.346 | G25: =SUM(G13:G24) -> -37888.216 | H25: =SUM(H13:H24) -> -17591.346 | I25: =SUM(I13:I24) -> -13127.346 | ... M25: =SUM(M13:M24) -> -25511.096 | N25: =SUM(B25:M25) -> -289483.57
A27: FLUSSO DI CASSA NETTO | B27: =B10+B25 -> -1917.746 | C27: =C10+C25 -> 12030.254 | D27: =D10+D25 -> -433.74602 | E27: =E10+E25 -> 8293.254 | F27: =F10+F25 -> 9049.254 | G27: =G10+G25 -> -13463.616 | H27: =H10+H25 -> 6833.254 | I27: =I10+I25 -> 8697.254 | ... M27: =M10+M25 -> -2608.496 | N27: =SUM(B27:M27) -> 16557.628
A28: Saldo cassa iniziale | B28: =SUMIFS(Parametri!$C$7:$C$8,Parametri!$G$7:$G$8,1) -> 145000 | C28: =B29 -> 143082.25 | D28: =C29 -> 155112.51 | E28: =D29 -> 154678.76 | F28: =E29 -> 162972.02 | G28: =F29 -> 172021.27 | H28: =G29 -> 158557.65 | I28: =H29 -> 165390.91 | J28: =I29 -> 174088.16 | ... M28: =L29 -> 164166.12 | N28: =B28 -> 145000
A29: SALDO CASSA FINALE | B29: =B28+B27 -> 143082.25 | C29: =C28+C27 -> 155112.51 | D29: =D28+D27 -> 154678.76 | E29: =E28+E27 -> 162972.02 | F29: =F28+F27 -> 172021.27 | G29: =G28+G27 -> 158557.65 | H29: =H28+H27 -> 165390.91 | I29: =I28+I27 -> 174088.16 | ... M29: =M28+M27 -> 161557.63 | N29: =M29 -> 161557.63

Sheet Proiezione 5 anni
A1: Proiezione di medio-lungo termine (5 anni)
A2: Anno 1 = Cash Flow mensile; anni successivi con ISTAT, inflazione costi, rate mutui residue e riserva manutenzioni
A4: Voce | B4: =Parametri!$B$4+0 -> 2027 | C4: =Parametri!$B$4+1 -> 2028 | D4: =Parametri!$B$4+2 -> 2029 | E4: =Parametri!$B$4+3 -> 2030 | F4: =Parametri!$B$4+4 -> 2031 | G4: Totale 5 anni
A5: Canoni netti (dopo morosità) | B5: ='Cash Flow'!N6+'Cash Flow'!N7 -> 269441.2 | C5: =B5*(1+Parametri!$B$16)^1 -> 274830.02 | D5: =B5*(1+Parametri!$B$16)^2 -> 280326.62 | E5: =B5*(1+Parametri!$B$16)^3 -> 285933.16 | F5: =B5*(1+Parametri!$B$16)^4 -> 291651.82 | G5: =SUM(B5:F5) -> 1402182.8
A6: Entrate straordinarie (rateizzazioni, vendite) | B6: ='Cash Flow'!N8+'Cash Flow'!N9 -> 36600 | C6: =0 -> 0 | D6: =0 -> 0 | E6: =0 -> 0 | F6: =0 -> 0 | G6: =SUM(B6:F6) -> 36600
A7: Rate mutui | B7: =-SUMIFS(Mutui!$P$5:$P$8,Mutui!$O$5:$O$8,1) -> -112650.95 | C7: =-SUMIFS(Mutui!$Q$5:$Q$8,Mutui!$O$5:$O$8,1) -> -112650.95 | D7: =-SUMIFS(Mutui!$R$5:$R$8,Mutui!$O$5:$O$8,1) -> -99924.77 | E7: =-SUMIFS(Mutui!$S$5:$S$8,Mutui!$O$5:$O$8,1) -> -87198.588 | F7: =-SUMIFS(Mutui!$T$5:$T$8,Mutui!$O$5:$O$8,1) -> -87198.588 | G7: =SUM(B7:F7) -> -499623.85
A8: IMU | B8: ='Cash Flow'!N14 -> -24521.62 | C8: =$B$8 -> -24521.62 | D8: =$B$8 -> -24521.62 | E8: =$B$8 -> -24521.62 | F8: =$B$8 -> -24521.62 | G8: =SUM(B8:F8) -> -122608.1
A9: Costi operativi ricorrenti | B9: ='Cash Flow'!N15+'Cash Flow'!N16+'Cash Flow'!N17+'Cash Flow'!N19+'Cash Flow'!N20+'Cash Flow'!N21+'Cash Flow'!N22 -> -89461 | C9: =$B$9*(1+Parametri!$B$17)^1 -> -91250.22 | D9: =$B$9*(1+Parametri!$B$17)^2 -> -93075.224 | E9: =$B$9*(1+Parametri!$B$17)^3 -> -94936.729 | F9: =$B$9*(1+Parametri!$B$17)^4 -> -96835.463 | G9: =SUM(B9:F9) -> -465558.64
A10: Manutenzioni straordinarie | B10: ='Cash Flow'!N18 -> -22500 | C10: =-Immobili!$H$17*Parametri!$B$18*(1+Parametri!$B$17)^1 -> -22225.8 | D10: =-Immobili!$H$17*Parametri!$B$18*(1+Parametri!$B$17)^2 -> -22670.316 | E10: =-Immobili!$H$17*Parametri!$B$18*(1+Parametri!$B$17)^3 -> -23123.722 | F10: =-Immobili!$H$17*Parametri!$B$18*(1+Parametri!$B$17)^4 -> -23586.197 | G10: =SUM(B10:F10) -> -114106.04
A11: Investimenti e spese commerciali | B11: ='Cash Flow'!N23+'Cash Flow'!N24 -> -40350 | C11: =0 -> 0 | D11: =0 -> 0 | E11: =0 -> 0 | F11: =0 -> 0 | G11: =SUM(B11:F11) -> -40350
A12: FLUSSO NETTO | B12: =SUM(B5:B11) -> 16557.628 | C12: =SUM(C5:C11) -> 24181.432 | D12: =SUM(D5:D11) -> 40134.694 | E12: =SUM(E5:E11) -> 56152.498 | F12: =SUM(F5:F11) -> 59509.952 | G12: =SUM(B12:F12) -> 196536.2
A13: Saldo cassa iniziale | B13: ='Cash Flow'!B28 -> 145000 | C13: =B14 -> 161557.63 | D13: =C14 -> 185739.06 | E13: =D14 -> 225873.75 | F13: =E14 -> 282026.25 | G13: =B13 -> 145000
A14: SALDO CASSA FINALE | B14: =B13+B12 -> 161557.63 | C14: =C13+C12 -> 185739.06 | D14: =D13+D12 -> 225873.75 | E14: =E13+E12 -> 282026.25 | F14: =F13+F12 -> 341536.2 | G14: =F14 -> 341536.2
A15: Debito residuo mutui fine anno (stima) | B15: =Mutui!$I$9 -> 800381.2 | C15: =MAX(0,B15-(-C7)*0.7) -> 721525.53 | D15: =MAX(0,C15-(-D7)*0.7) -> 651578.19 | E15: =MAX(0,D15-(-E7)*0.7) -> 590539.18 | F15: =MAX(0,E15-(-F7)*0.7) -> 529500.17 | G15: =F15 -> 529500.17
A17: Nota: il debito residuo dagli anni successivi è stimato (quota capitale ≈ 70% delle rate).

Sheet KPI Patrimonio
A1: KPI del patrimonio immobiliare
A2: Per società e totale (indipendente dal filtro)
A4: Indicatore | B4: IU | C4: ID | D4: Totale
A5: Numero immobili | B5: =COUNTIFS(Immobili!$B$5:$B$16,"IU") -> 6 | C5: =COUNTIFS(Immobili!$B$5:$B$16,"ID") -> 6 | D5: =SUM(B5:C5) -> 12
A6: Valore di mercato patrimonio | B6: =SUMIFS(Immobili!$H$5:$H$16,Immobili!$B$5:$B$16,"IU") -> 2600000 | C6: =SUMIFS(Immobili!$H$5:$H$16,Immobili!$B$5:$B$16,"ID") -> 1758000 | D6: =SUM(B6:C6) -> 4358000
A7: Canone annuo potenziale | B7: =SUMIFS(Immobili!$I$5:$I$16,Immobili!$B$5:$B$16,"IU")*12 -> 168840 | C7: =SUMIFS(Immobili!$I$5:$I$16,Immobili!$B$5:$B$16,"ID")*12 -> 112560 | D7: =SUM(B7:C7) -> 281400
A8: Canone annuo effettivo (dopo sfitti) | B8: =SUMIFS(Immobili!$R$5:$R$16,Immobili!$B$5:$B$16,"IU") -> 168840 | C8: =SUMIFS(Immobili!$R$5:$R$16,Immobili!$B$5:$B$16,"ID") -> 106100 | D8: =SUM(B8:C8) -> 274940
A9: Tasso di occupazione | B9: =IFERROR(SUMIFS(Immobili!$P$5:$P$16,Immobili!$B$5:$B$16,"IU")/(COUNTIFS(Immobili!$B$5:$B$16,"IU")*12),0) -> 1 | C9: =IFERROR(SUMIFS(Immobili!$P$5:$P$16,Immobili!$B$5:$B$16,"ID")/(COUNTIFS(Immobili!$B$5:$B$16,"ID")*12),0) -> 0.76388889 | D9: =IFERROR(SUM(Immobili!$P$5:$P$16)/(D5*12),0) -> 0.88194444
A10: Mancato incasso per sfitto | B10: =B7-B8 -> 0 | C10: =C7-C8 -> 6460 | D10: =SUM(B10:C10) -> 6460
A11: IMU annua | B11: =SUMIFS(Immobili!$U$5:$U$16,Immobili!$B$5:$B$16,"IU") -> 15612.05 | C11: =SUMIFS(Immobili!$U$5:$U$16,Immobili!$B$5:$B$16,"ID") -> 8909.57 | D11: =SUM(B11:C11) -> 24521.62
A12: Imposta di registro | B12: =SUMIFS(Immobili!$V$5:$V$16,Immobili!$B$5:$B$16,"IU") -> 1984.8 | C12: =SUMIFS(Immobili!$V$5:$V$16,Immobili!$B$5:$B$16,"ID") -> 1368 | D12: =SUM(B12:C12) -> 3352.8
A13: Manutenzioni (ord. + straord.) | B13: =SUMIFS(Immobili!$N$5:$N$16,Immobili!$B$5:$B$16,"IU")+SUMIFS(Immobili!$W$5:$W$16,Immobili!$B$5:$B$16,"IU") -> 21650 | C13: =SUMIFS(Immobili!$N$5:$N$16,Immobili!$B$5:$B$16,"ID")+SUMIFS(Immobili!$W$5:$W$16,Immobili!$B$5:$B$16,"ID") -> 8550 | D13: =SUM(B13:C13) -> 30200
A14: Costi totali immobili | B14: =SUMIFS(Immobili!$X$5:$X$16,Immobili!$B$5:$B$16,"IU") -> 45846.85 | C14: =SUMIFS(Immobili!$X$5:$X$16,Immobili!$B$5:$B$16,"ID") -> 26987.57 | D14: =SUM(B14:C14) -> 72834.42
A15: Rendimento lordo potenziale | B15: =IFERROR(B7/B6,0) -> 0.064938462 | C15: =IFERROR(C7/C6,0) -> 0.064027304 | D15: =IFERROR(D7/D6,0) -> 0.064570904
A16: Rendimento lordo effettivo | B16: =IFERROR(B8/B6,0) -> 0.064938462 | C16: =IFERROR(C8/C6,0) -> 0.060352673 | D16: =IFERROR(D8/D6,0) -> 0.063088573
A17: Rendimento netto (ante imposte dirette e oneri finanziari) | B17: =IFERROR((B8-B14)/B6,0) -> 0.047305058 | C17: =IFERROR((C8-C14)/C6,0) -> 0.045001382 | D17: =IFERROR((D8-D14)/D6,0) -> 0.046375764
A18: Incidenza manutenzioni su canoni | B18: =IFERROR(B13/B8,0) -> 0.12822791 | C18: =IFERROR(C13/C8,0) -> 0.080584354 | D18: =IFERROR(D13/D8,0) -> 0.10984215
A19: Debito residuo mutui 01/01 | B19: =SUMIFS(Mutui!$E$5:$E$8,Mutui!$A$5:$A$8,"IU") -> 630000 | C19: =SUMIFS(Mutui!$E$5:$E$8,Mutui!$A$5:$A$8,"ID") -> 250000 | D19: =SUM(B19:C19) -> 880000
A20: Interessi passivi anno | B20: =SUMIFS(Mutui!$K$5:$K$8,Mutui!$A$5:$A$8,"IU") -> 24440.67 | C20: =SUMIFS(Mutui!$K$5:$K$8,Mutui!$A$5:$A$8,"ID") -> 8591.4781 | D20: =SUM(B20:C20) -> 33032.148
A21: LTV (debito / valore) | B21: =IFERROR(B19/B6,0) -> 0.24230769 | C21: =IFERROR(C19/C6,0) -> 0.14220705 | D21: =IFERROR(D19/D6,0) -> 0.20192749
A22: Rendimento netto dopo interessi | B22: =IFERROR((B8-B14-B20)/B6,0) -> 0.0379048 | C22: =IFERROR((C8-C14-C20)/C6,0) -> 0.040114307 | D22: =IFERROR((D8-D14-D20)/D6,0) -> 0.038796106

Sheet Parametri
A1: Parametri generali
A3: Filtro società (Tutte / IU / ID) | B3: Tutte
A4: Anno di previsione | B4: 2027
A6: Codice | B6: Ragione sociale | C6: Saldo cassa 01/01 | D6: IRES+IRAP annua stimata | E6: Assicurazioni annue | F6: Commercialista / consulenze mensili | G6: Incluso | I6: Categoria | J6: Moltipl. | L6: Comune | M6: Aliquota IMU anno prec. ‰ | N6: Aliquota IMU anno corr. ‰
A7: IU | B7: Immobiliare Uno S.r.l. | C7: 85000 | D7: 18000 | E7: 6200 | F7: 650 | G7: =IF(OR($B$3="Tutte",A7=$B$3),1,0) -> 1 | I7: A/1 | J7: 160 | L7: Napoli | M7: 10.6 | N7: 10.6
A8: ID | B8: Immobiliare Due S.r.l. | C8: 60000 | D8: 12000 | E8: 4800 | F8: 550 | G8: =IF(OR($B$3="Tutte",A8=$B$3),1,0) -> 1 | I8: A/2 | J8: 160 | L8: Pozzuoli | M8: 10.6 | N8: 10.6
I9: A/3 | J9: 160 | L9: Casoria | M9: 10.6 | N9: 10.6
I10: A/4 | J10: 160 | L10: Caserta | M10: 10.6 | N10: 10.6
A11: % imprevisti (accantonamento su canoni) | B11: 0.03 | I11: A/7 | J11: 160 | L11: Salerno | M11: 10.4 | N11: 10.6
A12: % morosità attesa sui canoni | B12: 0.02 | I12: A/8 | J12: 160
A13: Mese pagamento assicurazioni (1-12) | B13: 1 | I13: A/10 | J13: 80
A14: % acconto imposte dirette a giugno | B14: 0.4 | I14: B/1 | J14: 140
A15: % acconto imposte dirette a novembre | B15: 0.6 | I15: C/1 | J15: 55
A16: Adeguamento ISTAT canoni annuo (proiezione) | B16: 0.02 | I16: C/2 | J16: 160
A17: Inflazione costi annua (proiezione) | B17: 0.02 | I17: C/3 | J17: 140
A18: Riserva manut. straordinaria (% valore patrimonio / anno) | B18: 0.005 | I18: C/6 | J18: 160
I19: C/7 | J19: 160
I20: D/1 | J20: 65
I21: D/5 | J21: 80
I22: D/7 | J22: 65
I23: D/8 | J23: 65

Sheet Immobili
A1: Anagrafica immobili e redditività
A2: Dati demo – IMU calcolata su rendita rivalutata 5% × moltiplicatore × aliquota comunale
A4: Codice | B4: Società | C4: Descrizione | D4: Comune | E4: Tipo | F4: Cat. | G4: Rendita catastale | H4: Valore di mercato | I4: Canone mensile | J4: Inquilino | K4: Mese rinnovo registro | L4: % registro | M4: Condominio mensile | N4: Manut. ordinaria annua | O4: Bene merce | P4: Mesi locati | Q4: Mesi locati 1° sem. | R4: Canone annuo effettivo | S4: Base imponibile IMU | T4: IMU acconto (giugno) | U4: IMU annua | V4: Registro annuo | W4: Manut. straordinaria anno | X4: Costi totali anno | Y4: Rend. lordo potenziale | Z4: Rend. lordo effettivo | AA4: Rend. netto | AB4: Incidenza costi su canoni | AC4: Incluso
A5: IU-01 | B5: IU | C5: Ufficio Centro Direzionale Is. E3 | D5: Napoli | E5: Commerciale | F5: A/10 | G5: 2450 | H5: 420000 | I5: 2300 | J5: Studio Legale Ferraro | K5: 3 | L5: 0.01 | M5: 180 | N5: 600 | O5: Sì | P5: =SUM(Occupazione!C5:N5) -> 12 | Q5: =SUM(Occupazione!C5:H5) -> 6 | R5: =I5*P5 -> 27600 | S5: =G5*1.05*VLOOKUP(F5,Parametri!$I$7:$J$23,2,0) -> 205800 | T5: =ROUND(S5*VLOOKUP(D5,Parametri!$L$7:$N$11,2,0)/1000*IF(O5="Sì",Q5,6)/12,2) -> 1090.74 | U5: =ROUND(S5*VLOOKUP(D5,Parametri!$L$7:$N$11,3,0)/1000*IF(O5="Sì",P5,12)/12,2) -> 2181.48 | V5: =IF(P5>0,I5*12*L5,0) -> 276 | W5: =-SUMIFS(Straordinari!$F$5:$F$64,Straordinari!$C$5:$C$64,A5,Straordinari!$D$5:$D$64,"Manutenzione straordinaria") -> 0 | X5: =U5+V5+M5*12+N5+W5 -> 5217.48 | Y5: =IFERROR(I5*12/H5,0) -> 0.065714286 | Z5: =IFERROR(R5/H5,0) -> 0.065714286 | AA5: =IFERROR((R5-X5)/H5,0) -> 0.053291714 | AB5: =IFERROR(X5/R5,0) -> 0.18903913 | AC5: =IF(OR(Parametri!$B$3="Tutte",B5=Parametri!$B$3),1,0) -> 1
A6: IU-02 | B6: IU | C6: Negozio Via Toledo | D6: Napoli | E6: Commerciale | F6: C/1 | G6: 3900 | H6: 580000 | I6: 3800 | J6: Bar Toledo S.n.c. | K6: 9 | L6: 0.01 | M6: 120 | N6: 900 | O6: Sì | P6: =SUM(Occupazione!C6:N6) -> 12 | Q6: =SUM(Occupazione!C6:H6) -> 6 | R6: =I6*P6 -> 45600 | S6: =G6*1.05*VLOOKUP(F6,Parametri!$I$7:$J$23,2,0) -> 225225 | T6: =ROUND(S6*VLOOKUP(D6,Parametri!$L$7:$N$11,2,0)/1000*IF(O6="Sì",Q6,6)/12,2) -> 1193.69 | U6: =ROUND(S6*VLOOKUP(D6,Parametri!$L$7:$N$11,3,0)/1000*IF(O6="Sì",P6,12)/12,2) -> 2387.39 | V6: =IF(P6>0,I6*12*L6,0) -> 456 | W6: =-SUMIFS(Straordinari!$F$5:$F$64,Straordinari!$C$5:$C$64,A6,Straordinari!$D$5:$D$64,"Manutenzione straordinaria") -> 4200 | X6: =U6+V6+M6*12+N6+W6 -> 9383.39 | Y6: =IFERROR(I6*12/H6,0) -> 0.07862069 | Z6: =IFERROR(R6/H6,0) -> 0.07862069 | AA6: =IFERROR((R6-X6)/H6,0) -> 0.062442431 | AB6: =IFERROR(X6/R6,0) -> 0.2057761 | AC6: =IF(OR(Parametri!$B$3="Tutte",B6=Parametri!$B$3),1,0) -> 1
A7: IU-03 | B7: IU | C7: Appartamento Vomero | D7: Napoli | E7: Abitativo | F7: A/2 | G7: 1280 | H7: 390000 | I7: 1450 | J7: Marco De Luca | K7: 5 | L7: 0.02 | M7: 160 | N7: 500 | O7: Sì | P7: =SUM(Occupazione!C7:N7) -> 12 | Q7: =SUM(Occupazione!C7:H7) -> 6 | R7: =I7*P7 -> 17400 | S7: =G7*1.05*VLOOKUP(F7,Parametri!$I$7:$J$23,2,0) -> 215040 | T7: =ROUND(S7*VLOOKUP(D7,Parametri!$L$7:$N$11,2,0)/1000*IF(O7="Sì",Q7,6)/12,2) -> 1139.71 | U7: =ROUND(S7*VLOOKUP(D7,Parametri!$L$7:$N$11,3,0)/1000*IF(O7="Sì",P7,12)/12,2) -> 2279.42 | V7: =IF(P7>0,I7*12*L7,0) -> 348 | W7: =-SUMIFS(Straordinari!$F$5:$F$64,Straordinari!$C$5:$C$64,A7,Straordinari!$D$5:$D$64,"Manutenzione straordinaria") -> 0 | X7: =U7+V7+M7*12+N7+W7 -> 5047.42 | Y7: =IFERROR(I7*12/H7,0) -> 0.044615385 | Z7: =IFERROR(R7/H7,0) -> 0.044615385 | AA7: =IFERROR((R7-X7)/H7,0) -> 0.031673282 | AB7: =IFERROR(X7/R7,0) -> 0.29008161 | AC7: =IF(OR(Parametri!$B$3="Tutte",B7=Parametri!$B$3),1,0) -> 1
A8: IU-04 | B8: IU | C8: Appartamento Via Napoli | D8: Pozzuoli | E8: Abitativo | F8: A/3 | G8: 780 | H8: 230000 | I8: 900 | J8: Anna Esposito | K8: 11 | L8: 0.02 | M8: 90 | N8: 400 | O8: Sì | P8: =SUM(Occupazione!C8:N8) -> 12 | Q8: =SUM(Occupazione!C8:H8) -> 6 | R8: =I8*P8 -> 10800 | S8: =G8*1.05*VLOOKUP(F8,Parametri!$I$7:$J$23,2,0) -> 131040 | T8: =ROUND(S8*VLOOKUP(D8,Parametri!$L$7:$N$11,2,0)/1000*IF(O8="Sì",Q8,6)/12,2) -> 694.51 | U8: =ROUND(S8*VLOOKUP(D8,Parametri!$L$7:$N$11,3,0)/1000*IF(O8="Sì",P8,12)/12,2) -> 1389.02 | V8: =IF(P8>0,I8*12*L8,0) -> 216 | W8: =-SUMIFS(Straordinari!$F$5:$F$64,Straordinari!$C$5:$C$64,A8,Straordinari!$D$5:$D$64,"Manutenzione straordinaria") -> 0 | X8: =U8+V8+M8*12+N8+W8 -> 3085.02 | Y8: =IFERROR(I8*12/H8,0) -> 0.046956522 | Z8: =IFERROR(R8/H8,0) -> 0.046956522 | AA8: =IFERROR((R8-X8)/H8,0) -> 0.033543391 | AB8: =IFERROR(X8/R8,0) -> 0.28565 | AC8: =IF(OR(Parametri!$B$3="Tutte",B8=Parametri!$B$3),1,0) -> 1
A9: IU-05 | B9: IU | C9: Box auto Via Napoli | D9: Pozzuoli | E9: Pertinenza | F9: C/6 | G9: 160 | H9: 30000 | I9: 120 | J9: Anna Esposito | K9: 11 | L9: 0.02 | M9: 0 | N9: 50 | O9: Sì | P9: =SUM(Occupazione!C9:N9) -> 12 | Q9: =SUM(Occupazione!C9:H9) -> 6 | R9: =I9*P9 -> 1440 | S9: =G9*1.05*VLOOKUP(F9,Parametri!$I$7:$J$23,2,0) -> 26880 | T9: =ROUND(S9*VLOOKUP(D9,Parametri!$L$7:$N$11,2,0)/1000*IF(O9="Sì",Q9,6)/12,2) -> 142.46 | U9: =ROUND(S9*VLOOKUP(D9,Parametri!$L$7:$N$11,3,0)/1000*IF(O9="Sì",P9,12)/12,2) -> 284.93 | V9: =IF(P9>0,I9*12*L9,0) -> 28.8 | W9: =-SUMIFS(Straordinari!$F$5:$F$64,Straordinari!$C$5:$C$64,A9,Straordinari!$D$5:$D$64,"Manutenzione straordinaria") -> 0 | X9: =U9+V9+M9*12+N9+W9 -> 363.73 | Y9: =IFERROR(I9*12/H9,0) -> 0.048 | Z9: =IFERROR(R9/H9,0) -> 0.048 | AA9: =IFERROR((R9-X9)/H9,0) -> 0.035875667 | AB9: =IFERROR(X9/R9,0) -> 0.25259028 | AC9: =IF(OR(Parametri!$B$3="Tutte",B9=Parametri!$B$3),1,0) -> 1
A10: IU-06 | B10: IU | C10: Capannone logistico | D10: Casoria | E10: Commerciale | F10: D/7 | G10: 9800 | H10: 950000 | I10: 5500 | J10: Logistica Campana S.p.A. | K10: 1 | L10: 0.01 | M10: 0 | N10: 2500 | O10: No | P10: =SUM(Occupazione!C10:N10) -> 12 | Q10: =SUM(Occupazione!C10:H10) -> 6 | R10: =I10*P10 -> 66000 | S10: =G10*1.05*VLOOKUP(F10,Parametri!$I$7:$J$23,2,0) -> 668850 | T10: =ROUND(S10*VLOOKUP(D10,Parametri!$L$7:$N$11,2,0)/1000*IF(O10="Sì",Q10,6)/12,2) -> 3544.91 | U10: =ROUND(S10*VLOOKUP(D10,Parametri!$L$7:$N$11,3,0)/1000*IF(O10="Sì",P10,12)/12,2) -> 7089.81 | V10: =IF(P10>0,I10*12*L10,0) -> 660 | W10: =-SUMIFS(Straordinari!$F$5:$F$64,Straordinari!$C$5:$C$64,A10,Straordinari!$D$5:$D$64,"Manutenzione straordinaria") -> 12500 | X10: =U10+V10+M10*12+N10+W10 -> 22749.81 | Y10: =IFERROR(I10*12/H10,0) -> 0.069473684 | Z10: =IFERROR(R10/H10,0) -> 0.069473684 | AA10: =IFERROR((R10-X10)/H10,0) -> 0.045526516 | AB10: =IFERROR(X10/R10,0) -> 0.34469409 | AC10: =IF(OR(Parametri!$B$3="Tutte",B10=Parametri!$B$3),1,0) -> 1
A11: ID-01 | B11: ID | C11: Appartamento Corso Trieste | D11: Caserta | E11: Abitativo | F11: A/2 | G11: 1050 | H11: 260000 | I11: 1000 | J11: Luca Russo | K11: 6 | L11: 0.02 | M11: 110 | N11: 450 | O11: Sì | P11: =SUM(Occupazione!C11:N11) -> 12 | Q11: =SUM(Occupazione!C11:H11) -> 6 | R11: =I11*P11 -> 12000 | S11: =G11*1.05*VLOOKUP(F11,Parametri!$I$7:$J$23,2,0) -> 176400 | T11: =ROUND(S11*VLOOKUP(D11,Parametri!$L$7:$N$11,2,0)/1000*IF(O11="Sì",Q11,6)/12,2) -> 934.92 | U11: =ROUND(S11*VLOOKUP(D11,Parametri!$L$7:$N$11,3,0)/1000*IF(O11="Sì",P11,12)/12,2) -> 1869.84 | V11: =IF(P11>0,I11*12*L11,0) -> 240 | W11: =-SUMIFS(Straordinari!$F$5:$F$64,Straordinari!$C$5:$C$64,A11,Straordinari!$D$5:$D$64,"Manutenzione straordinaria") -> 0 | X11: =U11+V11+M11*12+N11+W11 -> 3879.84 | Y11: =IFERROR(I11*12/H11,0) -> 0.046153846 | Z11: =IFERROR(R11/H11,0) -> 0.046153846 | AA11: =IFERROR((R11-X11)/H11,0) -> 0.031231385 | AB11: =IFERROR(X11/R11,0) -> 0.32332 | AC11: =IF(OR(Parametri!$B$3="Tutte",B11=Parametri!$B$3),1,0) -> 1
A12: ID-02 | B12: ID | C12: Ufficio Via Roma | D12: Caserta | E12: Commerciale | F12: A/10 | G12: 1900 | H12: 300000 | I12: 1700 | J12: Assicurazioni Vesuvio S.r.l. | K12: 4 | L12: 0.01 | M12: 140 | N12: 500 | O12: Sì | P12: =SUM(Occupazione!C12:N12) -> 12 | Q12: =SUM(Occupazione!C12:H12) -> 6 | R12: =I12*P12 -> 20400 | S12: =G12*1.05*VLOOKUP(F12,Parametri!$I$7:$J$23,2,0) -> 159600 | T12: =ROUND(S12*VLOOKUP(D12,Parametri!$L$7:$N$11,2,0)/1000*IF(O12="Sì",Q12,6)/12,2) -> 845.88 | U12: =ROUND(S12*VLOOKUP(D12,Parametri!$L$7:$N$11,3,0)/1000*IF(O12="Sì",P12,12)/12,2) -> 1691.76 | V12: =IF(P12>0,I12*12*L12,0) -> 204 | W12: =-SUMIFS(Straordinari!$F$5:$F$64,Straordinari!$C$5:$C$64,A12,Straordinari!$D$5:$D$64,"Manutenzione straordinaria") -> 1100 | X12: =U12+V12+M12*12+N12+W12 -> 5175.76 | Y12: =IFERROR(I12*12/H12,0) -> 0.068 | Z12: =IFERROR(R12/H12,0) -> 0.068 | AA12: =IFERROR((R12-X12)/H12,0) -> 0.050747467 | AB12: =IFERROR(X12/R12,0) -> 0.25371373 | AC12: =IF(OR(Parametri!$B$3="Tutte",B12=Parametri!$B$3),1,0) -> 1
A13: ID-03 | B13: ID | C13: Negozio Corso Vittorio Emanuele | D13: Salerno | E13: Commerciale | F13: C/1 | G13: 2700 | H13: 410000 | I13: 2600 | J13: Ottica Salernitana S.r.l. | K13: 2 | L13: 0.01 | M13: 100 | N13: 700 | O13: Sì | P13: =SUM(Occupazione!C13:N13) -> 12 | Q13: =SUM(Occupazione!C13:H13) -> 6 | R13: =I13*P13 -> 31200 | S13: =G13*1.05*VLOOKUP(F13,Parametri!$I$7:$J$23,2,0) -> 155925 | T13: =ROUND(S13*VLOOKUP(D13,Parametri!$L$7:$N$11,2,0)/1000*IF(O13="Sì",Q13,6)/12,2) -> 810.81 | U13: =ROUND(S13*VLOOKUP(D13,Parametri!$L$7:$N$11,3,0)/1000*IF(O13="Sì",P13,12)/12,2) -> 1652.81 | V13: =IF(P13>0,I13*12*L13,0) -> 312 | W13: =-SUMIFS(Straordinari!$F$5:$F$64,Straordinari!$C$5:$C$64,A13,Straordinari!$D$5:$D$64,"Manutenzione straordinaria") -> 0 | X13: =U13+V13+M13*12+N13+W13 -> 3864.81 | Y13: =IFERROR(I13*12/H13,0) -> 0.076097561 | Z13: =IFERROR(R13/H13,0) -> 0.076097561 | AA13: =IFERROR((R13-X13)/H13,0) -> 0.066671195 | AB13: =IFERROR(X13/R13,0) -> 0.12387212 | AC13: =IF(OR(Parametri!$B$3="Tutte",B13=Parametri!$B$3),1,0) -> 1
A14: ID-04 | B14: ID | C14: Appartamento Lungomare | D14: Salerno | E14: Abitativo | F14: A/3 | G14: 900 | H14: 250000 | I14: 1100 | J14: Giulia Ferri (disdetta 31/03) | K14: 7 | L14: 0.02 | M14: 120 | N14: 450 | O14: Sì | P14: =SUM(Occupazione!C14:N14) -> 7 | Q14: =SUM(Occupazione!C14:H14) -> 3 | R14: =I14*P14 -> 7700 | S14: =G14*1.05*VLOOKUP(F14,Parametri!$I$7:$J$23,2,0) -> 151200 | T14: =ROUND(S14*VLOOKUP(D14,Parametri!$L$7:$N$11,2,0)/1000*IF(O14="Sì",Q14,6)/12,2) -> 393.12 | U14: =ROUND(S14*VLOOKUP(D14,Parametri!$L$7:$N$11,3,0)/1000*IF(O14="Sì",P14,12)/12,2) -> 934.92 | V14: =IF(P14>0,I14*12*L14,0) -> 264 | W14: =-SUMIFS(Straordinari!$F$5:$F$64,Straordinari!$C$5:$C$64,A14,Straordinari!$D$5:$D$64,"Manutenzione straordinaria") -> 4700 | X14: =U14+V14+M14*12+N14+W14 -> 7788.92 | Y14: =IFERROR(I14*12/H14,0) -> 0.0528 | Z14: =IFERROR(R14/H14,0) -> 0.0308 | AA14: =IFERROR((R14-X14)/H14,0) -> -0.00035568 | AB14: =IFERROR(X14/R14,0) -> 1.0115481 | AC14: =IF(OR(Parametri!$B$3="Tutte",B14=Parametri!$B$3),1,0) -> 1
A15: ID-05 | B15: ID | C15: Ufficio Centro Direzionale Is. G1 | D15: Napoli | E15: Commerciale | F15: A/10 | G15: 3100 | H15: 520000 | I15: 2900 | J15: Tech Partners S.r.l. | K15: 10 | L15: 0.01 | M15: 210 | N15: 650 | O15: Sì | P15: =SUM(Occupazione!C15:N15) -> 12 | Q15: =SUM(Occupazione!C15:H15) -> 6 | R15: =I15*P15 -> 34800 | S15: =G15*1.05*VLOOKUP(F15,Parametri!$I$7:$J$23,2,0) -> 260400 | T15: =ROUND(S15*VLOOKUP(D15,Parametri!$L$7:$N$11,2,0)/1000*IF(O15="Sì",Q15,6)/12,2) -> 1380.12 | U15: =ROUND(S15*VLOOKUP(D15,Parametri!$L$7:$N$11,3,0)/1000*IF(O15="Sì",P15,12)/12,2) -> 2760.24 | V15: =IF(P15>0,I15*12*L15,0) -> 348 | W15: =-SUMIFS(Straordinari!$F$5:$F$64,Straordinari!$C$5:$C$64,A15,Straordinari!$D$5:$D$64,"Manutenzione straordinaria") -> 0 | X15: =U15+V15+M15*12+N15+W15 -> 6278.24 | Y15: =IFERROR(I15*12/H15,0) -> 0.066923077 | Z15: =IFERROR(R15/H15,0) -> 0.066923077 | AA15: =IFERROR((R15-X15)/H15,0) -> 0.054849538 | AB15: =IFERROR(X15/R15,0) -> 0.1804092 | AC15: =IF(OR(Parametri!$B$3="Tutte",B15=Parametri!$B$3),1,0) -> 1
A16: ID-06 | B16: ID | C16: Posto auto Via Pergolesi | D16: Pozzuoli | E16: Pertinenza | F16: C/6 | G16: 95 | H16: 18000 | I16: 80 | J16: (sfitto) | K16: 1 | L16: 0.02 | M16: 0 | N16: 0 | O16: Sì | P16: =SUM(Occupazione!C16:N16) -> 0 | Q16: =SUM(Occupazione!C16:H16) -> 0 | R16: =I16*P16 -> 0 | S16: =G16*1.05*VLOOKUP(F16,Parametri!$I$7:$J$23,2,0) -> 15960 | T16: =ROUND(S16*VLOOKUP(D16,Parametri!$L$7:$N$11,2,0)/1000*IF(O16="Sì",Q16,6)/12,2) -> 0 | U16: =ROUND(S16*VLOOKUP(D16,Parametri!$L$7:$N$11,3,0)/1000*IF(O16="Sì",P16,12)/12,2) -> 0 | V16: =IF(P16>0,I16*12*L16,0) -> 0 | W16: =-SUMIFS(Straordinari!$F$5:$F$64,Straordinari!$C$5:$C$64,A16,Straordinari!$D$5:$D$64,"Manutenzione straordinaria") -> 0 | X16: =U16+V16+M16*12+N16+W16 -> 0 | Y16: =IFERROR(I16*12/H16,0) -> 0.053333333 | Z16: =IFERROR(R16/H16,0) -> 0 | AA16: =IFERROR((R16-X16)/H16,0) -> 0 | AB16: =IFERROR(X16/R16,0) -> 0 | AC16: =IF(OR(Parametri!$B$3="Tutte",B16=Parametri!$B$3),1,0) -> 1
A17: TOTALE (filtro) | H17: =SUMPRODUCT($AC$5:$AC$16,H5:H16) -> 4358000 | I17: =SUMPRODUCT($AC$5:$AC$16,I5:I16) -> 23450 | R17: =SUMPRODUCT($AC$5:$AC$16,R5:R16) -> 274940 | T17: =SUMPRODUCT($AC$5:$AC$16,T5:T16) -> 12170.87 | U17: =SUMPRODUCT($AC$5:$AC$16,U5:U16) -> 24521.62 | V17: =SUMPRODUCT($AC$5:$AC$16,V5:V16) -> 3352.8 | W17: =SUMPRODUCT($AC$5:$AC$16,W5:W16) -> 22500 | X17: =SUMPRODUCT($AC$5:$AC$16,X5:X16) -> 72834.42 | Y17: =IFERROR(I17*12/H17,0) -> 0.064570904 | Z17: =IFERROR(R17/H17,0) -> 0.063088573 | AA17: =IFERROR((R17-X17)/H17,0) -> 0.046375764 | AB17: =IFERROR(X17/R17,0) -> 0.26491023

Sheet Occupazione
A1: Piano di occupazione 2027
A2: 1 = locato, 0 = sfitto
A4: Codice | B4: Inquilino | C4: Gen | D4: Feb | E4: Mar | F4: Apr | G4: Mag | H4: Giu | I4: Lug | J4: Ago | K4: Set | L4: Ott | M4: Nov | N4: Dic | O4: Mesi locati
A5: =Immobili!A5 -> IU-01 | B5: =Immobili!J5 -> Studio Legale Ferraro | C5: 1 | D5: 1 | E5: 1 | F5: 1 | G5: 1 | H5: 1 | I5: 1 | J5: 1 | K5: 1 | L5: 1 | M5: 1 | N5: 1 | O5: =SUM(C5:N5) -> 12
A6: =Immobili!A6 -> IU-02 | B6: =Immobili!J6 -> Bar Toledo S.n.c. | C6: 1 | D6: 1 | E6: 1 | F6: 1 | G6: 1 | H6: 1 | I6: 1 | J6: 1 | K6: 1 | L6: 1 | M6: 1 | N6: 1 | O6: =SUM(C6:N6) -> 12
A7: =Immobili!A7 -> IU-03 | B7: =Immobili!J7 -> Marco De Luca | C7: 1 | D7: 1 | E7: 1 | F7: 1 | G7: 1 | H7: 1 | I7: 1 | J7: 1 | K7: 1 | L7: 1 | M7: 1 | N7: 1 | O7: =SUM(C7:N7) -> 12
A8: =Immobili!A8 -> IU-04 | B8: =Immobili!J8 -> Anna Esposito | C8: 1 | D8: 1 | E8: 1 | F8: 1 | G8: 1 | H8: 1 | I8: 1 | J8: 1 | K8: 1 | L8: 1 | M8: 1 | N8: 1 | O8: =SUM(C8:N8) -> 12
A9: =Immobili!A9 -> IU-05 | B9: =Immobili!J9 -> Anna Esposito | C9: 1 | D9: 1 | E9: 1 | F9: 1 | G9: 1 | H9: 1 | I9: 1 | J9: 1 | K9: 1 | L9: 1 | M9: 1 | N9: 1 | O9: =SUM(C9:N9) -> 12
A10: =Immobili!A10 -> IU-06 | B10: =Immobili!J10 -> Logistica Campana S.p.A. | C10: 1 | D10: 1 | E10: 1 | F10: 1 | G10: 1 | H10: 1 | I10: 1 | J10: 1 | K10: 1 | L10: 1 | M10: 1 | N10: 1 | O10: =SUM(C10:N10) -> 12
A11: =Immobili!A11 -> ID-01 | B11: =Immobili!J11 -> Luca Russo | C11: 1 | D11: 1 | E11: 1 | F11: 1 | G11: 1 | H11: 1 | I11: 1 | J11: 1 | K11: 1 | L11: 1 | M11: 1 | N11: 1 | O11: =SUM(C11:N11) -> 12
A12: =Immobili!A12 -> ID-02 | B12: =Immobili!J12 -> Assicurazioni Vesuvio S.r.l. | C12: 1 | D12: 1 | E12: 1 | F12: 1 | G12: 1 | H12: 1 | I12: 1 | J12: 1 | K12: 1 | L12: 1 | M12: 1 | N12: 1 | O12: =SUM(C12:N12) -> 12
A13: =Immobili!A13 -> ID-03 | B13: =Immobili!J13 -> Ottica Salernitana S.r.l. | C13: 1 | D13: 1 | E13: 1 | F13: 1 | G13: 1 | H13: 1 | I13: 1 | J13: 1 | K13: 1 | L13: 1 | M13: 1 | N13: 1 | O13: =SUM(C13:N13) -> 12
A14: =Immobili!A14 -> ID-04 | B14: =Immobili!J14 -> Giulia Ferri (disdetta 31/03) | C14: 1 | D14: 1 | E14: 1 | F14: 0 | G14: 0 | H14: 0 | I14: 0 | J14: 0 | K14: 1 | L14: 1 | M14: 1 | N14: 1 | O14: =SUM(C14:N14) -> 7
A15: =Immobili!A15 -> ID-05 | B15: =Immobili!J15 -> Tech Partners S.r.l. | C15: 1 | D15: 1 | E15: 1 | F15: 1 | G15: 1 | H15: 1 | I15: 1 | J15: 1 | K15: 1 | L15: 1 | M15: 1 | N15: 1 | O15: =SUM(C15:N15) -> 12
A16: =Immobili!A16 -> ID-06 | B16: =Immobili!J16 -> (sfitto) | C16: 0 | D16: 0 | E16: 0 | F16: 0 | G16: 0 | H16: 0 | I16: 0 | J16: 0 | K16: 0 | L16: 0 | M16: 0 | N16: 0 | O16: =SUM(C16:N16) -> 0

Sheet Mutui
A1: Mutui e finanziamenti
A2: Rata francese; simulazione surroga/rinegoziazione sul debito residuo
A4: Società | B4: Descrizione | C4: Banca | D4: Immobili a garanzia | E4: Debito residuo 01/01 | F4: TAN attuale | G4: Rate residue | H4: Rata mensile | I4: Debito residuo 31/12 | J4: Quota capitale anno | K4: Interessi anno | L4: TAN ipotesi surroga | M4: Rata con surroga | N4: Risparmio annuo surroga | O4: Incluso | P4: Rate anno 1 | Q4: Rate anno 2 | R4: Rate anno 3 | S4: Rate anno 4 | T4: Rate anno 5
A5: IU | B5: Mutuo ipotecario Napoli | C5: Intesa Sanpaolo | D5: IU-01, IU-02 | E5: 250000 | F5: 0.038 | G5: 144 | H5: =PMT(F5/12,G5,-E5) -> 2164.6244 | I5: =-FV(F5/12,MIN(12,G5),-H5,E5) -> 233234.51 | J5: =E5-I5 -> 16765.491 | K5: =H5*MIN(12,G5)-J5 -> 9210.0012 | L5: 0.031 | M5: =PMT(L5/12,G5,-E5) -> 2081.2185 | N5: =(H5-M5)*12 -> 1000.8711 | O5: =IF(OR(Parametri!$B$3="Tutte",A5=Parametri!$B$3),1,0) -> 1 | P5: =H5*MAX(0,MIN(12,G5-12*0)) -> 25975.493 | Q5: =H5*MAX(0,MIN(12,G5-12*1)) -> 25975.493 | R5: =H5*MAX(0,MIN(12,G5-12*2)) -> 25975.493 | S5: =H5*MAX(0,MIN(12,G5-12*3)) -> 25975.493 | T5: =H5*MAX(0,MIN(12,G5-12*4)) -> 25975.493
A6: IU | B6: Mutuo capannone | C6: BPER Banca | D6: IU-06 | E6: 380000 | F6: 0.041 | G6: 180 | H6: =PMT(F6/12,G6,-E6) -> 2829.8948 | I6: =-FV(F6/12,MIN(12,G6),-H6,E6) -> 361271.93 | J6: =E6-I6 -> 18728.068 | K6: =H6*MIN(12,G6)-J6 -> 15230.669 | L6: 0.034 | M6: =PMT(L6/12,G6,-E6) -> 2697.9311 | N6: =(H6-M6)*12 -> 1583.5642 | O6: =IF(OR(Parametri!$B$3="Tutte",A6=Parametri!$B$3),1,0) -> 1 | P6: =H6*MAX(0,MIN(12,G6-12*0)) -> 33958.737 | Q6: =H6*MAX(0,MIN(12,G6-12*1)) -> 33958.737 | R6: =H6*MAX(0,MIN(12,G6-12*2)) -> 33958.737 | S6: =H6*MAX(0,MIN(12,G6-12*3)) -> 33958.737 | T6: =H6*MAX(0,MIN(12,G6-12*4)) -> 33958.737
A7: ID | B7: Mutuo ipotecario Caserta/Salerno | C7: UniCredit | D7: ID-01, ID-02, ID-03 | E7: 190000 | F7: 0.035 | G7: 96 | H7: =PMT(F7/12,G7,-E7) -> 2272.0298 | I7: =-FV(F7/12,MIN(12,G7),-H7,E7) -> 169051.72 | J7: =E7-I7 -> 20948.283 | K7: =H7*MIN(12,G7)-J7 -> 6316.0751 | L7: 0.03 | M7: =PMT(L7/12,G7,-E7) -> 2228.6187 | N7: =(H7-M7)*12 -> 520.93393 | O7: =IF(OR(Parametri!$B$3="Tutte",A7=Parametri!$B$3),1,0) -> 1 | P7: =H7*MAX(0,MIN(12,G7-12*0)) -> 27264.358 | Q7: =H7*MAX(0,MIN(12,G7-12*1)) -> 27264.358 | R7: =H7*MAX(0,MIN(12,G7-12*2)) -> 27264.358 | S7: =H7*MAX(0,MIN(12,G7-12*3)) -> 27264.358 | T7: =H7*MAX(0,MIN(12,G7-12*4)) -> 27264.358
A8: ID | B8: Finanziamento chirografario | C8: BCC Campania | D8: - | E8: 60000 | F8: 0.046 | G8: 30 | H8: =PMT(F8/12,G8,-E8) -> 2121.0304 | I8: =-FV(F8/12,MIN(12,G8),-H8,E8) -> 36823.039 | J8: =E8-I8 -> 23176.961 | K8: =H8*MIN(12,G8)-J8 -> 2275.403 | L8: 0.046 | M8: =PMT(L8/12,G8,-E8) -> 2121.0304 | N8: =(H8-M8)*12 -> 0 | O8: =IF(OR(Parametri!$B$3="Tutte",A8=Parametri!$B$3),1,0) -> 1 | P8: =H8*MAX(0,MIN(12,G8-12*0)) -> 25452.364 | Q8: =H8*MAX(0,MIN(12,G8-12*1)) -> 25452.364 | R8: =H8*MAX(0,MIN(12,G8-12*2)) -> 12726.182 | S8: =H8*MAX(0,MIN(12,G8-12*3)) -> 0 | T8: =H8*MAX(0,MIN(12,G8-12*4)) -> 0
A9: TOTALE (filtro) | E9: =SUMPRODUCT($O$5:$O$8,E5:E8) -> 880000 | H9: =SUMPRODUCT($O$5:$O$8,H5:H8) -> 9387.5794 | I9: =SUMPRODUCT($O$5:$O$8,I5:I8) -> 800381.2 | J9: =SUMPRODUCT($O$5:$O$8,J5:J8) -> 79618.804 | K9: =SUMPRODUCT($O$5:$O$8,K5:K8) -> 33032.148 | M9: =SUMPRODUCT($O$5:$O$8,M5:M8) -> 9128.7986 | N9: =SUMPRODUCT($O$5:$O$8,N5:N8) -> 3105.3693 | P9: =SUMPRODUCT($O$5:$O$8,P5:P8) -> 112650.95 | Q9: =SUMPRODUCT($O$5:$O$8,Q5:Q8) -> 112650.95 | R9: =SUMPRODUCT($O$5:$O$8,R5:R8) -> 99924.77 | S9: =SUMPRODUCT($O$5:$O$8,S5:S8) -> 87198.588 | T9: =SUMPRODUCT($O$5:$O$8,T5:T8) -> 87198.588

Sheet Straordinari
A1: Movimenti straordinari previsti
A2: Importi + entrata / − uscita. Categorie: Manutenzione straordinaria, Rateizzazione arretrati, Compravendita, Commerciale, Altro
A4: Data | B4: Società | C4: Immobile | D4: Categoria | E4: Descrizione | F4: Importo | G4: Incluso
A5: 46492 | B5: ID | C5: ID-04 | D5: Manutenzione straordinaria | E5: Ritinteggiatura fine contratto | F5: -2800 | G5: =IF(B5="",0,IF(OR(Parametri!$B$3="Tutte",B5=Parametri!$B$3),1,0)) -> 1
A6: 46517 | B6: ID | C6: ID-04 | D6: Manutenzione straordinaria | E6: Revisione completa impianti | F6: -1900 | G6: =IF(B6="",0,IF(OR(Parametri!$B$3="Tutte",B6=Parametri!$B$3),1,0)) -> 1
A7: 46558 | B7: ID | C7: ID-04 | D7: Commerciale | E7: Annunci Immobiliare.it / Idealista | F7: -350 | G7: =IF(B7="",0,IF(OR(Parametri!$B$3="Tutte",B7=Parametri!$B$3),1,0)) -> 1
A8: 46573 | B8: IU | C8: IU-02 | D8: Manutenzione straordinaria | E8: Sostituzione climatizzatore | F8: -4200 | G8: =IF(B8="",0,IF(OR(Parametri!$B$3="Tutte",B8=Parametri!$B$3),1,0)) -> 1
A9: 46464 | B9: IU | C9: IU-06 | D9: Manutenzione straordinaria | E9: Rifacimento guaina copertura | F9: -12500 | G9: =IF(B9="",0,IF(OR(Parametri!$B$3="Tutte",B9=Parametri!$B$3),1,0)) -> 1
A10: 46672 | B10: ID | C10: ID-02 | D10: Manutenzione straordinaria | E10: Infiltrazione infisso | F10: -1100 | G10: =IF(B10="",0,IF(OR(Parametri!$B$3="Tutte",B10=Parametri!$B$3),1,0)) -> 1
A11: 46446 | B11: ID | C11: ID-03 | D11: Rateizzazione arretrati | E11: Ottica Salernitana - rata 1/6 | F11: 2600 | G11: =IF(B11="",0,IF(OR(Parametri!$B$3="Tutte",B11=Parametri!$B$3),1,0)) -> 1
A12: 46477 | B12: ID | C12: ID-03 | D12: Rateizzazione arretrati | E12: Ottica Salernitana - rata 2/6 | F12: 2600 | G12: =IF(B12="",0,IF(OR(Parametri!$B$3="Tutte",B12=Parametri!$B$3),1,0)) -> 1
A13: 46507 | B13: ID | C13: ID-03 | D13: Rateizzazione arretrati | E13: Ottica Salernitana - rata 3/6 | F13: 2600 | G13: =IF(B13="",0,IF(OR(Parametri!$B$3="Tutte",B13=Parametri!$B$3),1,0)) -> 1
A14: 46538 | B14: ID | C14: ID-03 | D14: Rateizzazione arretrati | E14: Ottica Salernitana - rata 4/6 | F14: 2600 | G14: =IF(B14="",0,IF(OR(Parametri!$B$3="Tutte",B14=Parametri!$B$3),1,0)) -> 1
A15: 46568 | B15: ID | C15: ID-03 | D15: Rateizzazione arretrati | E15: Ottica Salernitana - rata 5/6 | F15: 2600 | G15: =IF(B15="",0,IF(OR(Parametri!$B$3="Tutte",B15=Parametri!$B$3),1,0)) -> 1
A16: 46599 | B16: ID | C16: ID-03 | D16: Rateizzazione arretrati | E16: Ottica Salernitana - rata 6/6 | F16: 2600 | G16: =IF(B16="",0,IF(OR(Parametri!$B$3="Tutte",B16=Parametri!$B$3),1,0)) -> 1
... A18: 46721 | B18: ID | C18: ID-06 | D18: Compravendita | E18: Vendita posto auto Via Pergolesi | F18: 21000 | G18: =IF(B18="",0,IF(OR(Parametri!$B$3="Tutte",B18=Parametri!$B$3),1,0)) -> 1
G19: =IF(B19="",0,IF(OR(Parametri!$B$3="Tutte",B19=Parametri!$B$3),1,0)) -> 0
G20: =IF(B20="",0,IF(OR(Parametri!$B$3="Tutte",B20=Parametri!$B$3),1,0)) -> 0
G21: =IF(B21="",0,IF(OR(Parametri!$B$3="Tutte",B21=Parametri!$B$3),1,0)) -> 0
G22: =IF(B22="",0,IF(OR(Parametri!$B$3="Tutte",B22=Parametri!$B$3),1,0)) -> 0
G23: =IF(B23="",0,IF(OR(Parametri!$B$3="Tutte",B23=Parametri!$B$3),1,0)) -> 0
G24: =IF(B24="",0,IF(OR(Parametri!$B$3="Tutte",B24=Parametri!$B$3),1,0)) -> 0
G25: =IF(B25="",0,IF(OR(Parametri!$B$3="Tutte",B25=Parametri!$B$3),1,0)) -> 0
G26: =IF(B26="",0,IF(OR(Parametri!$B$3="Tutte",B26=Parametri!$B$3),1,0)) -> 0
G27: =IF(B27="",0,IF(OR(Parametri!$B$3="Tutte",B27=Parametri!$B$3),1,0)) -> 0
G28: =IF(B28="",0,IF(OR(Parametri!$B$3="Tutte",B28=Parametri!$B$3),1,0)) -> 0
G29: =IF(B29="",0,IF(OR(Parametri!$B$3="Tutte",B29=Parametri!$B$3),1,0)) -> 0
G30: =IF(B30="",0,IF(OR(Parametri!$B$3="Tutte",B30=Parametri!$B$3),1,0)) -> 0
... G64: =IF(B64="",0,IF(OR(Parametri!$B$3="Tutte",B64=Parametri!$B$3),1,0)) -> 0
